main.py
mseep_yonote_mcp-0.1.1.dist-info/METADATA
mseep_yonote_mcp-0.1.1.dist-info/WHEEL
mseep_yonote_mcp-0.1.1.dist-info/entry_points.txt
mseep_yonote_mcp-0.1.1.dist-info/top_level.txt
mseep_yonote_mcp-0.1.1.dist-info/RECORD
