Metadata-Version: 2.4
Name: mseep-yonote-mcp
Version: 0.1.1
Summary: Add your description here
Author-email: mseep <support@skydeck.ai>
Requires-Python: >=3.13
Requires-Dist: fast-agent-mcp>=0.2.23
Requires-Dist: requests>=2.32.3
